{"Floor":{"Type":"Default","Script Components":{},"Engine Components":{"Transform":{"position_x":0.0,"position_y":0.0,"position_z":0.0,"rotation_x":0.0,"rotation_y":-0.0,"rotation_z":0.0,"scale_x":200.0,"scale_y":1.0,"scale_z":200.0},"Renderable3D":{"model uid":842303435,"diffuse uid":2130157803,"emissive":0.0,"visible":true},"RigidStatic":{"Active":true,"StaticFriction":0.5,"DynamicFriction":0.5,"Restitution":0.5,"x extent":200.0,"y extent":1.0,"z extent":200.0,"Simulation":true,"Trigger":false,"scale lock":true,"shapeid":0,"PhysicsTypeid":5,"Offset x":0.0,"Offset y":0.0,"Offset z":0.0}},"Children":{}},"DirectionalLight":{"Type":"Default","Script Components":{},"Engine Components":{"Transform":{"position_x":3.0,"position_y":10.0,"position_z":3.0,"rotation_x":0.0,"rotation_y":-0.0,"rotation_z":0.0,"scale_x":1.0,"scale_y":1.0,"scale_z":1.0},"Renderable3D":{"model uid":1472377361,"diffuse uid":2130157803,"emissive":14.0,"visible":true},"DirectionalLight":{"colour_x":1.0,"colour_y":1.0,"colour_z":1.0,"ambient_x":0.800000011920929,"ambient_y":0.800000011920929,"ambient_z":0.800000011920929,"diffuse_x":1.0,"diffuse_y":1.0,"diffuse_z":1.0,"specular_x":0.0,"specular_y":0.0,"specular_z":0.0}},"Children":{}},"Player":{"Type":"Default","Script Components":{"C_ThirdPersonCamera":{},"C_ThirdPersonMovement":{}},"Engine Components":{"Transform":{"position_x":-0.005103792995214462,"position_y":1.9999971389770508,"position_z":-0.015059318393468857,"rotation_x":0.00619149673730135,"rotation_y":0.10647360235452652,"rotation_z":-0.006256858352571726,"scale_x":1.0,"scale_y":1.0,"scale_z":1.0},"PhysicsController":{"speed":0.0},"PlayerController":{}},"Children":{"Model":{"Type":"Default","Script Components":{"C_LerpToHeading":{}},"Engine Components":{"Transform":{"position_x":0.0,"position_y":0.0,"position_z":0.0,"rotation_x":1.3340212490220438e-8,"rotation_y":-0.000018749668015516363,"rotation_z":-5.718109719055064e-7,"scale_x":1.0,"scale_y":1.0,"scale_z":1.0},"Renderable3D":{"model uid":2058851582,"diffuse uid":658120761,"emissive":0.0,"visible":true}},"Children":{}}}},"Obstacles":{"Type":"Default","Script Components":{},"Engine Components":{},"Children":{"Box1":{"Type":"Default","Script Components":{},"Engine Components":{"Transform":{"position_x":-11.650975227355957,"position_y":3.156088352203369,"position_z":-6.898860454559326,"rotation_x":0.0,"rotation_y":-0.0,"rotation_z":0.0,"scale_x":4.099999904632568,"scale_y":4.099999904632568,"scale_z":4.099999904632568},"Renderable3D":{"model uid":842303435,"diffuse uid":2130157803,"emissive":0.0,"visible":true},"RigidStatic":{"Active":true,"StaticFriction":0.5,"DynamicFriction":0.5,"Restitution":0.5,"x extent":4.099999904632568,"y extent":4.099999904632568,"z extent":4.099999904632568,"Simulation":true,"Trigger":false,"scale lock":true,"shapeid":0,"PhysicsTypeid":5,"Offset x":0.0,"Offset y":0.0,"Offset z":0.0}},"Children":{}},"Box2":{"Type":"Default","Script Components":{},"Engine Components":{"Transform":{"position_x":-6.709044933319092,"position_y":-0.828716516494751,"position_z":-10.6076021194458,"rotation_x":0.0,"rotation_y":-0.0,"rotation_z":0.0,"scale_x":3.440000057220459,"scale_y":3.440000057220459,"scale_z":3.440000057220459},"Renderable3D":{"model uid":842303435,"diffuse uid":2130157803,"emissive":0.0,"visible":true},"RigidStatic":{"Active":true,"StaticFriction":0.5,"DynamicFriction":0.5,"Restitution":0.5,"x extent":3.440000057220459,"y extent":3.440000057220459,"z extent":3.440000057220459,"Simulation":true,"Trigger":false,"scale lock":true,"shapeid":0,"PhysicsTypeid":5,"Offset x":0.0,"Offset y":0.0,"Offset z":0.0}},"Children":{}}}}}