{"Tile3":{"Type":"Prefab","Transform":{"position_x":0.5,"position_y":0.0,"position_z":0.5,"rotation_x":0.0,"rotation_y":-0.0,"rotation_z":0.0,"scale_x":1.0,"scale_y":1.0,"scale_z":1.0}},"Tile3":{"Type":"Prefab","Transform":{"position_x":1.5,"position_y":0.0,"position_z":0.5,"rotation_x":0.0,"rotation_y":-0.0,"rotation_z":0.0,"scale_x":1.0,"scale_y":1.0,"scale_z":1.0}},"Tile3":{"Type":"Prefab","Transform":{"position_x":1.5,"position_y":0.0,"position_z":1.5,"rotation_x":0.0,"rotation_y":-0.0,"rotation_z":0.0,"scale_x":1.0,"scale_y":1.0,"scale_z":1.0}},"Tile3":{"Type":"Prefab","Transform":{"position_x":3.5,"position_y":0.0,"position_z":0.5,"rotation_x":0.0,"rotation_y":-0.0,"rotation_z":0.0,"scale_x":1.0,"scale_y":1.0,"scale_z":1.0}},"Tile3":{"Type":"Prefab","Transform":{"position_x":3.5,"position_y":0.0,"position_z":1.5,"rotation_x":0.0,"rotation_y":-0.0,"rotation_z":0.0,"scale_x":1.0,"scale_y":1.0,"scale_z":1.0}},"Tile3":{"Type":"Prefab","Transform":{"position_x":-1.5,"position_y":0.0,"position_z":1.5,"rotation_x":0.0,"rotation_y":-0.0,"rotation_z":0.0,"scale_x":1.0,"scale_y":1.0,"scale_z":1.0}},"Tile3":{"Type":"Prefab","Transform":{"position_x":-0.5,"position_y":-1.0,"position_z":2.5,"rotation_x":0.0,"rotation_y":-0.0,"rotation_z":0.0,"scale_x":1.0,"scale_y":1.0,"scale_z":1.0}},"Tile3":{"Type":"Prefab","Transform":{"position_x":0.5,"position_y":-1.0,"position_z":2.5,"rotation_x":0.0,"rotation_y":-0.0,"rotation_z":0.0,"scale_x":1.0,"scale_y":1.0,"scale_z":1.0}},"Tile3":{"Type":"Prefab","Transform":{"position_x":-0.5,"position_y":-1.0,"position_z":-1.5,"rotation_x":0.0,"rotation_y":-0.0,"rotation_z":0.0,"scale_x":1.0,"scale_y":1.0,"scale_z":1.0}},"Tile3":{"Type":"Prefab","Transform":{"position_x":0.5,"position_y":-1.0,"position_z":-2.5,"rotation_x":0.0,"rotation_y":-0.0,"rotation_z":0.0,"scale_x":1.0,"scale_y":1.0,"scale_z":1.0}},"Tile3":{"Type":"Prefab","Transform":{"position_x":1.5,"position_y":-1.0,"position_z":-2.5,"rotation_x":0.0,"rotation_y":-0.0,"rotation_z":0.0,"scale_x":1.0,"scale_y":1.0,"scale_z":1.0}},"Tile3":{"Type":"Prefab","Transform":{"position_x":2.5,"position_y":-1.0,"position_z":-2.5,"rotation_x":0.0,"rotation_y":-0.0,"rotation_z":0.0,"scale_x":1.0,"scale_y":1.0,"scale_z":1.0}},"Tile3":{"Type":"Prefab","Transform":{"position_x":2.5,"position_y":-1.0,"position_z":-1.5,"rotation_x":0.0,"rotation_y":-0.0,"rotation_z":0.0,"scale_x":1.0,"scale_y":1.0,"scale_z":1.0}}}